mumble_authenticator_templinks/__init__.py
mumble_authenticator_templinks/app.py
mumble_authenticator_templinks/authenticator.py
mumble_authenticator_templinks/config.py
mumble_authenticator_templinks/db.py
mumble_authenticator_templinks/decorators.py
mumble_authenticator_templinks/idlehandler.py
mumble_authenticator_templinks/logger.py
mumble_authenticator_templinks/main.py
mumble_authenticator_templinks/metacallback.py
mumble_authenticator_templinks/mixin_avatarcache.py
mumble_authenticator_templinks/mixin_basecache.py
mumble_authenticator_templinks/mixin_dataaccess.py
mumble_authenticator_templinks/mixin_idconversion.py
mumble_authenticator_templinks/password.py
mumble_authenticator_templinks/servercallback.py
mumble_authenticator_templinks/state.py
mumble_authenticator_templinks-2.0.8.dist-info/METADATA
mumble_authenticator_templinks-2.0.8.dist-info/WHEEL
mumble_authenticator_templinks-2.0.8.dist-info/entry_points.txt
mumble_authenticator_templinks-2.0.8.dist-info/RECORD
