Metadata-Version: 2.4
Name: mumble-authenticator-templinks
Version: 2.0.8
Summary: AllianceAuth Authenticator for Mumble server with support for templinks
Project-URL: homepage, https://gitlab.com/eveo7/mumble-authenticator-templinks
Author-email: Aaron Kable <aaronkable@gmail.com>, Adarnof <adarnof@gmail.com>, Ariel Rin <ozirascal@gmail.com>, Basraah <basraaheve@gmail.com>, Boris Talovikov <boris@talovikov.ru>, Eingang <eingang.vulpine@gmail.com>, Peter Pfeufer <info@ppfeufer.de>, Stefan Hacker <dd0t@users.sourceforge.net>
License-Expression: GPL-3.0-or-later
Keywords: allianceauth,authenticator,eveonline,mumble,templinks
Requires-Python: <3.13,>=3.12
Requires-Dist: bcrypt<5
Requires-Dist: diskcache<6.0.0,>=5.6.3
Requires-Dist: eveo7-mumbleserver-ice<0.1.0,>=0.0.4
Requires-Dist: passlib[bcrypt]<2.0.0,>=1.7.4
Requires-Dist: prometheus-client<0.23.0,>=0.22.1
Requires-Dist: pymysql<2.0.0,>=1.1.1
Requires-Dist: pyyaml<7.0.0,>=6.0.2
Requires-Dist: zeroc-ice<3.8,>=3.7.10.1
